LICENSE
README.md
setup.cfg
setup.py
skill_tree_parser.egg-info/PKG-INFO
skill_tree_parser.egg-info/SOURCES.txt
skill_tree_parser.egg-info/dependency_links.txt
skill_tree_parser.egg-info/requires.txt
skill_tree_parser.egg-info/top_level.txt
src/skill_tree/__init__.py
src/skill_tree/doc.py
src/skill_tree/img.py
src/skill_tree/init.py
src/skill_tree/tree.py
src/skill_tree/exercises/__init__.py
src/skill_tree/exercises/init_exercises.py
src/skill_tree/exercises/markdown.py
src/skill_tree/exercises/marked_math.py