Metadata-Version: 2.1
Name: skill-tree-parser
Version: 0.1.2
Summary: CSDN Skill Tree Parser
Home-page: https://gitcode.net/csdn/skill_tree_parser
Author: Liu Xin
Author-email: liuxin@csdn.net
License: MIT
Platform: UNKNOWN
Classifier: Topic :: Utilities
Classifier: Programming Language :: Python :: 3.5
Classifier: Programming Language :: Python :: 3.6
Classifier: Programming Language :: Python :: 3.7
Classifier: Programming Language :: Python :: 3.8
Classifier: Programming Language :: Python :: 3.9
Classifier: Programming Language :: Python :: 3 :: Only
Classifier: License :: OSI Approved :: MIT License
